__init__.py
kad_py/__init__.py
kad_py/command_utils.py
kad_py/example.py
kad_py/commands/__init__.py
kad_py/commands/capability.py
kad_py/commands/command.py
kad_py/commands/command_metadata.py
kad_py/commands/command_sig_data.py
kad_py/commands/cont_command.py
kad_py/commands/env_data.py
kad_py/commands/exec_command.py
kad_py/commands/sig.py
kad_py/commands/signer.py
kad_py/config/__init__.py
kad_py/config/constants.py
kad_py/config/setup.py
kad_py/docs/conf.py
kad_py/examples/example.py
kad_py/examples/testing_sign.py
kad_py/hashing_utils/__init__.py
kad_py/hashing_utils/encoding.py
kad_py/main/__init__.py
kad_py/main/kad_py_public.py
kad_py/main/kad_py_pvt.py
kad_py/pact_utils/__init__.py
kad_py/pact_utils/encoding.py
kad_py/sign/__init__.py
kad_py/sign/sign.py
kad_py/transactions/__init__.py
kad_py/transactions/pact_sign_transaction.py
kad_py/transactions/quicksign_transaction.py
kad_py/transactions/transaction.py
kad_py/utils/__init__.py
kad_py/utils/env_data.py
kad_py/utils/io_utils.py
kad_py/yaml_files/__init__.py
kad_py_lib-0.0.3.dist-info/LICENSE
kad_py_lib-0.0.3.dist-info/METADATA
kad_py_lib-0.0.3.dist-info/WHEEL
kad_py_lib-0.0.3.dist-info/top_level.txt
kad_py_lib-0.0.3.dist-info/RECORD
