Metadata-Version: 2.1
Name: kad_py_lib
Version: 0.0.3
Summary: A package to allow build and execute Kadena transactions in python
Author-email: Isoko <admin@isoko.xyz>
Maintainer-email: Mohannad Ahmad <mohannadwahmad97@gmail.com>
License: MIT License
Project-URL: Homepage, https://github.com/isokoxyz/kad_py
Project-URL: Issues, https://github.com/isokoxyz/kad_py/issues
Keywords: kadena
Classifier: Development Status :: 4 - Beta
Classifier: Intended Audience :: Developers
Classifier: Programming Language :: Python :: 3
Classifier: License :: OSI Approved :: MIT License
Classifier: Operating System :: OS Independent
Requires-Python: >=3.8
License-File: LICENSE
